{
  "OEE": {
    "text": "OEEDisplay",
    "id": 1,
    "parent": 0,
    "baseUrl": "",
    "moduleName": "OEEDisplay"
  },
  "OEECharts": {
    "text": "OEECharts",
    "id": 2,
    "parent": 1,
    "baseUrl": "js/modules/OEECharts/",
    "moduleName": "OEECharts"
  },
  "DowntimeColumnCharts": {
    "text": "DowntimeColumnCharts",
    "id": 3,
    "parent": 1,
    "baseUrl": "js/modules/DowntimeColumnCharts/",
    "moduleName": "DowntimeColumnCharts"
  },
  "DowntimeTimelineCharts": {
    "text": "DowntimeTimelineCharts",
    "id": 4,
    "parent": 1,
    "baseUrl": "js/modules/DowntimeTimelineCharts/",
    "moduleName": "DowntimeTimelineCharts"
  },
  "SystemConfiguration": {
    "text": "SystemConfiguration",
    "id": 5,
    "parent": 0,
    "baseUrl": "",
    "moduleName": "SystemConfiguration"
  },
  "UserConfiguration": {
    "text": "UserConfiguration",
    "id": 6,
    "parent": 5,
    "baseUrl": "js/modules/UserConfiguration/",
    "moduleName": "UserConfiguration"
  }
}
